tap_jotform/__init__.py
tap_jotform/__main__.py
tap_jotform/client.py
tap_jotform/streams.py
tap_jotform/tap.py
tap_jotform-0.7.2.dist-info/METADATA
tap_jotform-0.7.2.dist-info/WHEEL
tap_jotform-0.7.2.dist-info/entry_points.txt
tap_jotform-0.7.2.dist-info/licenses/LICENSE
tap_jotform-0.7.2.dist-info/RECORD
