Metadata-Version: 2.4
Name: tap-jotform
Version: 0.7.2
Summary: Singer tap for Jotform, built with the Meltano SDK for Singer Taps.
Project-URL: Documentation, https://github.com/reservoir-data/tap-jotform/#readme
Project-URL: Homepage, https://github.com/reservoir-data/tap-jotform
Project-URL: Repository, https://github.com/reservoir-data/tap-jotform
Author-email: Edgar Ramírez-Mondragón <edgarrm358@gmail.com>
Maintainer-email: Edgar Ramírez-Mondragón <edgarrm358@gmail.com>
License-Expression: Apache-2.0
License-File: LICENSE
Keywords: ELT,Jotform
Classifier: Programming Language :: Python :: 3 :: Only
Classifier: Programming Language :: Python :: 3.12
Classifier: Programming Language :: Python :: 3.13
Classifier: Programming Language :: Python :: 3.14
Requires-Python: >=3.12
Requires-Dist: colorama==0.4.*
Requires-Dist: requests-cache==1.2.*
Requires-Dist: singer-sdk==0.51.*
Requires-Dist: structlog==25.4.*
